LICENSE
MANIFEST.in
README.md
pyproject.toml
src/clusterondemandconfig/__init__.py
src/clusterondemandconfig/argparse_factory.py
src/clusterondemandconfig/command_context.py
src/clusterondemandconfig/config_file_encoding.py
src/clusterondemandconfig/config_namespace.py
src/clusterondemandconfig/configuration_validation.py
src/clusterondemandconfig/determine_invoked_command.py
src/clusterondemandconfig/exceptions.py
src/clusterondemandconfig/global_config.py
src/clusterondemandconfig/parser_utils.py
src/clusterondemandconfig/print_help.py
src/clusterondemandconfig/py.typed
src/clusterondemandconfig/testutils.py
src/clusterondemandconfig/config_dump/__init__.py
src/clusterondemandconfig/config_dump/full_ini_config_dump.py
src/clusterondemandconfig/config_dump/human_readable_config_dump.py
src/clusterondemandconfig/config_dump/minimal_ini_config_dump.py
src/clusterondemandconfig/config_dump/utils.py
src/clusterondemandconfig/configuration/__init__.py
src/clusterondemandconfig/configuration/collective_configuration.py
src/clusterondemandconfig/configuration/command_configuration.py
src/clusterondemandconfig/configuration/configuration.py
src/clusterondemandconfig/configuration/configuration_for_namespace_view.py
src/clusterondemandconfig/configuration/configuration_item.py
src/clusterondemandconfig/configuration/configuration_view.py
src/clusterondemandconfig/configuration/global_configuration.py
src/clusterondemandconfig/explain/__init__.py
src/clusterondemandconfig/explain/explain.py
src/clusterondemandconfig/explain/find_parameters.py
src/clusterondemandconfig/explain/namespace_tree.py
src/clusterondemandconfig/explain/template.mako
src/clusterondemandconfig/expression_parser/__init__.py
src/clusterondemandconfig/expression_parser/evaluator.py
src/clusterondemandconfig/expression_parser/grammar.py
src/clusterondemandconfig/expression_parser/lexeme_stream.py
src/clusterondemandconfig/expression_parser/parser.py
src/clusterondemandconfig/expression_parser/tokenizer.py
src/cm_cluster_on_demand_config.egg-info/PKG-INFO
src/cm_cluster_on_demand_config.egg-info/SOURCES.txt
src/cm_cluster_on_demand_config.egg-info/dependency_links.txt
src/cm_cluster_on_demand_config.egg-info/requires.txt
src/cm_cluster_on_demand_config.egg-info/top_level.txt