Metadata-Version: 2.4
Name: cm-cluster-on-demand-config
Version: 11.0.5
Summary: Base Command Manager COD configuration library
Author-email: Base Command Manager Cloud Team <sw-bright-cloud-team@nvidia.onmicrosoft.com>
License-Expression: Apache-2.0
Project-URL: Documentation, https://docs.nvidia.com/base-command-manager/
Classifier: Development Status :: 5 - Production/Stable
Classifier: Intended Audience :: Information Technology
Classifier: Intended Audience :: Science/Research
Classifier: Intended Audience :: System Administrators
Classifier: Programming Language :: Python :: 3 :: Only
Classifier: Programming Language :: Python :: 3.12
Classifier: Topic :: System :: Clustering
Classifier: Topic :: System :: Installation/Setup
Classifier: Topic :: System :: Monitoring
Classifier: Topic :: System :: Systems Administration
Requires-Python: >=3.12
License-File: LICENSE
Requires-Dist: mako>=0.8.1
Requires-Dist: PrettyTable>=3.4.0
Dynamic: license-file
